diffabs/__init__.py
diffabs/abs.py
diffabs/conc.py
diffabs/deeppoly.py
diffabs/interval.py
diffabs/utils.py
diffabs-0.1.dist-info/LICENSE
diffabs-0.1.dist-info/METADATA
diffabs-0.1.dist-info/WHEEL
diffabs-0.1.dist-info/top_level.txt
diffabs-0.1.dist-info/RECORD
