Metadata-Version: 2.1
Name: diffabs
Version: 0.1
Summary: Differentiable abstract domain implementations for neural network reasoning on PyTorch
Home-page: https://github.com/XuankangLin/DiffAbs
Author: Xuankang Lin
Author-email: xuankang.lin@gmail.com
License: UNKNOWN
Platform: UNKNOWN
Classifier: Programming Language :: Python :: 3
Classifier: Programming Language :: Python :: 3.7
Classifier: Programming Language :: Python :: 3.8
Classifier: License :: OSI Approved :: MIT License
Classifier: Operating System :: OS Independent
Requires-Python: >=3.7
Requires-Dist: torch (>=1.0.0)
